Workbook

Sheet README
A2: KVKK / GDPR VERİ TOPLAMA ÇALIŞMA KİTABI
A3: Privacy Due Diligence Kit — Departman Veri Toplama Formu
A5: BU DOSYA NEDİR?
A6: Bu çalışma kitabı, şirketinizin kişisel veri işleme faaliyetlerinin tespiti için hazırlanmıştır.
A7: Vereceğiniz cevaplar; KVKK veri envanteri, VERBİS kaydı, GDPR RoPA, aydınlatma metinleri,
A8: sözleşmeler ve politika setlerinin hazırlanmasında kullanılacaktır.
A10: KİM DOLDURACAK?
A11: Her sekme, adındaki departmanın yöneticisi/sorumlusu tarafından doldurulur.
A12: '01-Genel' sekmesini şirket yönetimi doldurur. '14-Entegrasyonlar' sekmesini BT koordine eder.
A13: '15-Kanıt Belgeleri' sekmesi tüm departmanların yükleyeceği belgelerin kontrol listesidir.
A15: NASIL DOLDURULACAK? — 10 ALTIN KURAL
A16: 1. Her satırdaki soruyu okuyun; 'Cevap/Açıklama' sütununa serbest metinle yanıt yazın.
... A66: Durum: Satırın doldurulma durumu — Dashboard'un veri kaynağıdır, mutlaka seçin.

Sheet 00-Dashboard
A1: 00-Dashboard — Doldurma İlerlemesi ve Risk Özeti (otomatik hesaplanır)
A3: Sekme | B3: Toplam Satır | C3: Dolduruldu | D3: Kısmen | E3: Bilinmiyor | F3: Uygulanamaz | G3: Boş | H3: Tamamlanma %
A4: 01-Genel-Sirket | B4: 45 | C4: =COUNTIF('01-Genel-Sirket'!$R$3:$R$47,"Dolduruldu") -> 0 | D4: =COUNTIF('01-Genel-Sirket'!$R$3:$R$47,"Kısmen Dolduruldu") -> 0 | E4: =COUNTIF('01-Genel-Sirket'!$R$3:$R$47,"Bilinmiyor") -> 0 | F4: =COUNTIF('01-Genel-Sirket'!$R$3:$R$47,"Uygulanamaz") -> 0 | G4: =B4-SUM(C4:F4) -> 45 | H4: =(C4+F4)/B4 -> 0
A5: 02-İnsan Kaynakları | B5: 106 | C5: =COUNTIF('02-İnsan Kaynakları'!$R$3:$R$108,"Dolduruldu") -> 0 | D5: =COUNTIF('02-İnsan Kaynakları'!$R$3:$R$108,"Kısmen Dolduruldu") -> 0 | E5: =COUNTIF('02-İnsan Kaynakları'!$R$3:$R$108,"Bilinmiyor") -> 0 | F5: =COUNTIF('02-İnsan Kaynakları'!$R$3:$R$108,"Uygulanamaz") -> 0 | G5: =B5-SUM(C5:F5) -> 106 | H5: =(C5+F5)/B5 -> 0
A6: 03-Bilgi Teknolojileri | B6: 160 | C6: =COUNTIF('03-Bilgi Teknolojileri'!$R$3:$R$162,"Dolduruldu") -> 0 | D6: =COUNTIF('03-Bilgi Teknolojileri'!$R$3:$R$162,"Kısmen Dolduruldu") -> 0 | E6: =COUNTIF('03-Bilgi Teknolojileri'!$R$3:$R$162,"Bilinmiyor") -> 0 | F6: =COUNTIF('03-Bilgi Teknolojileri'!$R$3:$R$162,"Uygulanamaz") -> 0 | G6: =B6-SUM(C6:F6) -> 160 | H6: =(C6+F6)/B6 -> 0
A7: 04-Yazılım Geliştirme | B7: 73 | C7: =COUNTIF('04-Yazılım Geliştirme'!$R$3:$R$75,"Dolduruldu") -> 0 | D7: =COUNTIF('04-Yazılım Geliştirme'!$R$3:$R$75,"Kısmen Dolduruldu") -> 0 | E7: =COUNTIF('04-Yazılım Geliştirme'!$R$3:$R$75,"Bilinmiyor") -> 0 | F7: =COUNTIF('04-Yazılım Geliştirme'!$R$3:$R$75,"Uygulanamaz") -> 0 | G7: =B7-SUM(C7:F7) -> 73 | H7: =(C7+F7)/B7 -> 0
A8: 05-Satış | B8: 55 | C8: =COUNTIF('05-Satış'!$R$3:$R$57,"Dolduruldu") -> 0 | D8: =COUNTIF('05-Satış'!$R$3:$R$57,"Kısmen Dolduruldu") -> 0 | E8: =COUNTIF('05-Satış'!$R$3:$R$57,"Bilinmiyor") -> 0 | F8: =COUNTIF('05-Satış'!$R$3:$R$57,"Uygulanamaz") -> 0 | G8: =B8-SUM(C8:F8) -> 55 | H8: =(C8+F8)/B8 -> 0
A9: 06-Pazarlama | B9: 65 | C9: =COUNTIF('06-Pazarlama'!$R$3:$R$67,"Dolduruldu") -> 0 | D9: =COUNTIF('06-Pazarlama'!$R$3:$R$67,"Kısmen Dolduruldu") -> 0 | E9: =COUNTIF('06-Pazarlama'!$R$3:$R$67,"Bilinmiyor") -> 0 | F9: =COUNTIF('06-Pazarlama'!$R$3:$R$67,"Uygulanamaz") -> 0 | G9: =B9-SUM(C9:F9) -> 65 | H9: =(C9+F9)/B9 -> 0
A10: 07-Sosyal Medya | B10: 40 | C10: =COUNTIF('07-Sosyal Medya'!$R$3:$R$42,"Dolduruldu") -> 0 | D10: =COUNTIF('07-Sosyal Medya'!$R$3:$R$42,"Kısmen Dolduruldu") -> 0 | E10: =COUNTIF('07-Sosyal Medya'!$R$3:$R$42,"Bilinmiyor") -> 0 | F10: =COUNTIF('07-Sosyal Medya'!$R$3:$R$42,"Uygulanamaz") -> 0 | G10: =B10-SUM(C10:F10) -> 40 | H10: =(C10+F10)/B10 -> 0
A11: 08-Muhasebe | B11: 48 | C11: =COUNTIF('08-Muhasebe'!$R$3:$R$50,"Dolduruldu") -> 0 | D11: =COUNTIF('08-Muhasebe'!$R$3:$R$50,"Kısmen Dolduruldu") -> 0 | E11: =COUNTIF('08-Muhasebe'!$R$3:$R$50,"Bilinmiyor") -> 0 | F11: =COUNTIF('08-Muhasebe'!$R$3:$R$50,"Uygulanamaz") -> 0 | G11: =B11-SUM(C11:F11) -> 48 | H11: =(C11+F11)/B11 -> 0
A12: 09-Satın Alma | B12: 40 | C12: =COUNTIF('09-Satın Alma'!$R$3:$R$42,"Dolduruldu") -> 0 | D12: =COUNTIF('09-Satın Alma'!$R$3:$R$42,"Kısmen Dolduruldu") -> 0 | E12: =COUNTIF('09-Satın Alma'!$R$3:$R$42,"Bilinmiyor") -> 0 | F12: =COUNTIF('09-Satın Alma'!$R$3:$R$42,"Uygulanamaz") -> 0 | G12: =B12-SUM(C12:F12) -> 40 | H12: =(C12+F12)/B12 -> 0
A13: 10-Hukuk | B13: 40 | C13: =COUNTIF('10-Hukuk'!$R$3:$R$42,"Dolduruldu") -> 0 | D13: =COUNTIF('10-Hukuk'!$R$3:$R$42,"Kısmen Dolduruldu") -> 0 | E13: =COUNTIF('10-Hukuk'!$R$3:$R$42,"Bilinmiyor") -> 0 | F13: =COUNTIF('10-Hukuk'!$R$3:$R$42,"Uygulanamaz") -> 0 | G13: =B13-SUM(C13:F13) -> 40 | H13: =(C13+F13)/B13 -> 0
A14: 11-Yönetim | B14: 35 | C14: =COUNTIF('11-Yönetim'!$R$3:$R$37,"Dolduruldu") -> 0 | D14: =COUNTIF('11-Yönetim'!$R$3:$R$37,"Kısmen Dolduruldu") -> 0 | E14: =COUNTIF('11-Yönetim'!$R$3:$R$37,"Bilinmiyor") -> 0 | F14: =COUNTIF('11-Yönetim'!$R$3:$R$37,"Uygulanamaz") -> 0 | G14: =B14-SUM(C14:F14) -> 35 | H14: =(C14+F14)/B14 -> 0
A15: 12-Güvenlik | B15: 40 | C15: =COUNTIF('12-Güvenlik'!$R$3:$R$42,"Dolduruldu") -> 0 | D15: =COUNTIF('12-Güvenlik'!$R$3:$R$42,"Kısmen Dolduruldu") -> 0 | E15: =COUNTIF('12-Güvenlik'!$R$3:$R$42,"Bilinmiyor") -> 0 | F15: =COUNTIF('12-Güvenlik'!$R$3:$R$42,"Uygulanamaz") -> 0 | G15: =B15-SUM(C15:F15) -> 40 | H15: =(C15+F15)/B15 -> 0
A16: 13-Temizlik | B16: 25 | C16: =COUNTIF('13-Temizlik'!$R$3:$R$27,"Dolduruldu") -> 0 | D16: =COUNTIF('13-Temizlik'!$R$3:$R$27,"Kısmen Dolduruldu") -> 0 | E16: =COUNTIF('13-Temizlik'!$R$3:$R$27,"Bilinmiyor") -> 0 | F16: =COUNTIF('13-Temizlik'!$R$3:$R$27,"Uygulanamaz") -> 0 | G16: =B16-SUM(C16:F16) -> 25 | H16: =(C16+F16)/B16 -> 0
A17: 14-Entegrasyonlar | B17: 57 | C17: =COUNTIF('14-Entegrasyonlar'!$N$3:$N$59,"Dolduruldu") -> 0 | D17: =COUNTIF('14-Entegrasyonlar'!$N$3:$N$59,"Kısmen Dolduruldu") -> 0 | E17: =COUNTIF('14-Entegrasyonlar'!$N$3:$N$59,"Bilinmiyor") -> 0 | F17: =COUNTIF('14-Entegrasyonlar'!$N$3:$N$59,"Uygulanamaz") -> 0 | G17: =B17-SUM(C17:F17) -> 57 | H17: =(C17+F17)/B17 -> 0
A18: 15-Kanıt Belgeleri (Eklendi) | B18: 75 | C18: =COUNTIF('15-Kanıt Belgeleri'!$F$3:$F$77,"Eklendi") -> 0 | D18: =COUNTIF('15-Kanıt Belgeleri'!$F$3:$F$77,"Eklenecek") -> 0 | E18: 0 | F18: =COUNTIF('15-Kanıt Belgeleri'!$F$3:$F$77,"Uygulanamaz") -> 0 | G18: =B18-SUM(C18:F18) -> 75 | H18: =(C18+F18)/B18 -> 0
A19: TOPLAM | B19: =SUM(B4:B18) -> 904 | C19: =SUM(C4:C18) -> 0 | D19: =SUM(D4:D18) -> 0 | E19: =SUM(E4:E18) -> 0 | F19: =SUM(F4:F18) -> 0 | G19: =SUM(G4:G18) -> 904 | H19: =(C19+F19)/B19 -> 0
A22: RİSK GÖSTERGELERİ
A23: Sekme | B23: Yurtdışı Aktarım 'Evet' | C23: Hukuki Sebep Belirsiz | D23: Doküman 'Yok' | E23: Kanıt 'Eklenecek'
A24: 01-Genel-Sirket | B24: =COUNTIF('01-Genel-Sirket'!$K$3:$K$47,"Evet") -> 0 | C24: =COUNTIF('01-Genel-Sirket'!$L$3:$L$47,"Belirlenmedi / Bilinmiyor") -> 0 | D24: =COUNTIF('01-Genel-Sirket'!$N$3:$N$47,"Yok") -> 0 | E24: =COUNTIF('01-Genel-Sirket'!$O$3:$O$47,"Eklenecek") -> 0
A25: 02-İnsan Kaynakları | B25: =COUNTIF('02-İnsan Kaynakları'!$K$3:$K$108,"Evet") -> 0 | C25: =COUNTIF('02-İnsan Kaynakları'!$L$3:$L$108,"Belirlenmedi / Bilinmiyor") -> 0 | D25: =COUNTIF('02-İnsan Kaynakları'!$N$3:$N$108,"Yok") -> 0 | E25: =COUNTIF('02-İnsan Kaynakları'!$O$3:$O$108,"Eklenecek") -> 0
A26: 03-Bilgi Teknolojileri | B26: =COUNTIF('03-Bilgi Teknolojileri'!$K$3:$K$162,"Evet") -> 0 | C26: =COUNTIF('03-Bilgi Teknolojileri'!$L$3:$L$162,"Belirlenmedi / Bilinmiyor") -> 0 | D26: =COUNTIF('03-Bilgi Teknolojileri'!$N$3:$N$162,"Yok") -> 0 | E26: =COUNTIF('03-Bilgi Teknolojileri'!$O$3:$O$162,"Eklenecek") -> 0
A27: 04-Yazılım Geliştirme | B27: =COUNTIF('04-Yazılım Geliştirme'!$K$3:$K$75,"Evet") -> 0 | C27: =COUNTIF('04-Yazılım Geliştirme'!$L$3:$L$75,"Belirlenmedi / Bilinmiyor") -> 0 | D27: =COUNTIF('04-Yazılım Geliştirme'!$N$3:$N$75,"Yok") -> 0 | E27: =COUNTIF('04-Yazılım Geliştirme'!$O$3:$O$75,"Eklenecek") -> 0
A28: 05-Satış | B28: =COUNTIF('05-Satış'!$K$3:$K$57,"Evet") -> 0 | C28: =COUNTIF('05-Satış'!$L$3:$L$57,"Belirlenmedi / Bilinmiyor") -> 0 | D28: =COUNTIF('05-Satış'!$N$3:$N$57,"Yok") -> 0 | E28: =COUNTIF('05-Satış'!$O$3:$O$57,"Eklenecek") -> 0
A29: 06-Pazarlama | B29: =COUNTIF('06-Pazarlama'!$K$3:$K$67,"Evet") -> 0 | C29: =COUNTIF('06-Pazarlama'!$L$3:$L$67,"Belirlenmedi / Bilinmiyor") -> 0 | D29: =COUNTIF('06-Pazarlama'!$N$3:$N$67,"Yok") -> 0 | E29: =COUNTIF('06-Pazarlama'!$O$3:$O$67,"Eklenecek") -> 0
A30: 07-Sosyal Medya | B30: =COUNTIF('07-Sosyal Medya'!$K$3:$K$42,"Evet") -> 0 | C30: =COUNTIF('07-Sosyal Medya'!$L$3:$L$42,"Belirlenmedi / Bilinmiyor") -> 0 | D30: =COUNTIF('07-Sosyal Medya'!$N$3:$N$42,"Yok") -> 0 | E30: =COUNTIF('07-Sosyal Medya'!$O$3:$O$42,"Eklenecek") -> 0
A31: 08-Muhasebe | B31: =COUNTIF('08-Muhasebe'!$K$3:$K$50,"Evet") -> 0 | C31: =COUNTIF('08-Muhasebe'!$L$3:$L$50,"Belirlenmedi / Bilinmiyor") -> 0 | D31: =COUNTIF('08-Muhasebe'!$N$3:$N$50,"Yok") -> 0 | E31: =COUNTIF('08-Muhasebe'!$O$3:$O$50,"Eklenecek") -> 0
A32: 09-Satın Alma | B32: =COUNTIF('09-Satın Alma'!$K$3:$K$42,"Evet") -> 0 | C32: =COUNTIF('09-Satın Alma'!$L$3:$L$42,"Belirlenmedi / Bilinmiyor") -> 0 | D32: =COUNTIF('09-Satın Alma'!$N$3:$N$42,"Yok") -> 0 | E32: =COUNTIF('09-Satın Alma'!$O$3:$O$42,"Eklenecek") -> 0
A33: 10-Hukuk | B33: =COUNTIF('10-Hukuk'!$K$3:$K$42,"Evet") -> 0 | C33: =COUNTIF('10-Hukuk'!$L$3:$L$42,"Belirlenmedi / Bilinmiyor") -> 0 | D33: =COUNTIF('10-Hukuk'!$N$3:$N$42,"Yok") -> 0 | E33: =COUNTIF('10-Hukuk'!$O$3:$O$42,"Eklenecek") -> 0
A34: 11-Yönetim | B34: =COUNTIF('11-Yönetim'!$K$3:$K$37,"Evet") -> 0 | C34: =COUNTIF('11-Yönetim'!$L$3:$L$37,"Belirlenmedi / Bilinmiyor") -> 0 | D34: =COUNTIF('11-Yönetim'!$N$3:$N$37,"Yok") -> 0 | E34: =COUNTIF('11-Yönetim'!$O$3:$O$37,"Eklenecek") -> 0
A35: 12-Güvenlik | B35: =COUNTIF('12-Güvenlik'!$K$3:$K$42,"Evet") -> 0 | C35: =COUNTIF('12-Güvenlik'!$L$3:$L$42,"Belirlenmedi / Bilinmiyor") -> 0 | D35: =COUNTIF('12-Güvenlik'!$N$3:$N$42,"Yok") -> 0 | E35: =COUNTIF('12-Güvenlik'!$O$3:$O$42,"Eklenecek") -> 0
A36: 13-Temizlik | B36: =COUNTIF('13-Temizlik'!$K$3:$K$27,"Evet") -> 0 | C36: =COUNTIF('13-Temizlik'!$L$3:$L$27,"Belirlenmedi / Bilinmiyor") -> 0 | D36: =COUNTIF('13-Temizlik'!$N$3:$N$27,"Yok") -> 0 | E36: =COUNTIF('13-Temizlik'!$O$3:$O$27,"Eklenecek") -> 0
A37: 14-Entegrasyonlar | B37: =COUNTIF('14-Entegrasyonlar'!$J$3:$J$59,"Evet") -> 0 | C37: =COUNTIF('14-Entegrasyonlar'!$K$3:$K$59,"Yok") -> 0 | D37: 0 | E37: 0
A39: Not: 14-Entegrasyonlar satırında 'Hukuki Sebep Belirsiz' sütunu, Sözleşme/DPA 'Yok' sayısını gösterir.

Sheet 01-Genel-Sirket
A1: 01-Genel-Sirket — Veri Toplama Formu
A2: No | B2: Bölüm | C2: Soru / Süreç | D2: Zorunlu? | E2: Cevap / Açıklama | F2: İşlenen Kişisel Veri | G2: İlgili Kişi Grubu | H2: Veri Kaynağı | I2: Kullanılan Sistem | J2: Veri Alıcısı | K2: Yurtdışı Aktarım | L2: Hukuki Sebep (KVKK → GDPR) | M2: Saklama Süresi | N2: Mevcut Doküman | O2: Kanıt Belgesi | P2: Risk / Not | Q2: Sorumlu | R2: Durum
A3: 1 | B3: Şirket Kimliği | C3: Şirketin tam ticari unvanı, MERSİS ve vergi numarası nedir? | D3: Zorunlu
A4: 2 | B4: Şirket Kimliği | C4: Ana faaliyet konusu ve NACE kodu nedir? | D4: Zorunlu
A5: 3 | B5: Şirket Kimliği | C5: Toplam çalışan sayısı kaçtır? (VERBİS eşiği için kritik) | D5: Zorunlu
A6: 4 | B6: Şirket Kimliği | C6: Yıllık mali bilanço toplamı hangi aralıktadır? (VERBİS eşiği için kritik) | D6: Zorunlu
A7: 5 | B7: Şirket Kimliği | C7: Şirketin kuruluş tarihi ve ticaret sicil bilgileri nedir? | D7: Zorunlu
A8: 6 | B8: Şirket Kimliği | C8: Şirketin web sitesi/alan adları nelerdir? | D8: Zorunlu
A9: 7 | B9: Şirket Kimliği | C9: Şirket hangi sektörel düzenlemelere tabidir? (BDDK, SPK, EPDK, Sağlık vb.) | D9: Zorunlu
A10: 8 | B10: Şirket Kimliği | C10: Yurt dışında müşterisi/kullanıcısı var mı? Hangi ülkelerde? (GDPR kapsamı için kritik) | D10: Zorunlu
A11: 9 | B11: Şirket Kimliği | C11: AB'de yerleşik kişilere mal/hizmet sunuluyor veya davranışları izleniyor mu? (GDPR m.3) | D11: Zorunlu
A12: 10 | B12: Şirket Kimliği | C12: Şirketin GDPR kapsamında AB temsilcisi (Art. 27) var mı? | D12: Opsiyonel
A13: 11 | B13: Grup & Ortaklık | C13: Grup şirketi yapısı var mı? Tüm grup şirketlerini listeleyin. | D13: Zorunlu
A14: 12 | B14: Grup & Ortaklık | C14: Ortaklık yapısı nedir? Yabancı ortak var mı? | D14: Zorunlu
... A47: 45 | B47: Mevcut KVKK Durumu | C47: Kurul'a yansıyan şikâyet, ihlal bildirimi veya idari yaptırım var mı? | D47: Zorunlu

Sheet 02-İnsan Kaynakları
A1: 02-İnsan Kaynakları — Veri Toplama Formu
A2: No | B2: Bölüm | C2: Soru / Süreç | D2: Zorunlu? | E2: Cevap / Açıklama | F2: İşlenen Kişisel Veri | G2: İlgili Kişi Grubu | H2: Veri Kaynağı | I2: Kullanılan Sistem | J2: Veri Alıcısı | K2: Yurtdışı Aktarım | L2: Hukuki Sebep (KVKK → GDPR) | M2: Saklama Süresi | N2: Mevcut Doküman | O2: Kanıt Belgesi | P2: Risk / Not | Q2: Sorumlu | R2: Durum
A3: 1 | B3: İşe Alım | C3: Aday başvuruları hangi kanallardan alınıyor? (Kariyer.net, LinkedIn, web, referans...) | D3: Zorunlu
A4: 2 | B4: İşe Alım | C4: İş ilanları hangi platformlarda yayınlanıyor? Platformlarla veri işleme sözleşmesi var mı? | D4: Zorunlu
A5: 3 | B5: İşe Alım | C5: CV'ler nerede saklanıyor? (ATS yazılımı, e-posta, klasör, fiziki dosya) | D5: Zorunlu
A6: 4 | B6: İşe Alım | C6: Olumsuz sonuçlanan aday CV'leri ne kadar süre saklanıyor? Aday havuzu var mı? | D6: Zorunlu
A7: 5 | B7: İşe Alım | C7: Aday havuzunda tutma için adaydan açık rıza alınıyor mu? | D7: Zorunlu
A8: 6 | B8: İşe Alım | C8: Adaylara aydınlatma metni sunuluyor mu? Hangi aşamada? | D8: Zorunlu
A9: 7 | B9: İşe Alım | C9: Mülakat notları ve değerlendirme formları tutuluyor mu? Nerede? | D9: Zorunlu
A10: 8 | B10: İşe Alım | C10: Kişilik envanteri, yetenek testi veya değerlendirme merkezi kullanılıyor mu? Hangi firma? | D10: Zorunlu
A11: 9 | B11: İşe Alım | C11: Referans kontrolü yapılıyor mu? Adayın bilgisi/rızası dahilinde mi? | D11: Zorunlu
A12: 10 | B12: İşe Alım | C12: Sosyal medya taraması yapılıyor mu? | D12: Zorunlu
A13: 11 | B13: İşe Alım | C13: Adli sicil kaydı isteniyor mu? Hangi pozisyonlar için ve hangi dayanakla? | D13: Zorunlu
A14: 12 | B14: İşe Alım | C14: İşe alım sürecinde dış danışmanlık/headhunter kullanılıyor mu? Sözleşmesi var mı? | D14: Zorunlu
... A108: 106 | B108: Yabancı & Stajyer | C108: Freelancer/danışman sözleşmelilerin verileri nasıl yönetiliyor? | D108: Opsiyonel

Sheet 03-Bilgi Teknolojileri
A1: 03-Bilgi Teknolojileri — Veri Toplama Formu
A2: No | B2: Bölüm | C2: Soru / Süreç | D2: Zorunlu? | E2: Cevap / Açıklama | F2: İşlenen Kişisel Veri | G2: İlgili Kişi Grubu | H2: Veri Kaynağı | I2: Kullanılan Sistem | J2: Veri Alıcısı | K2: Yurtdışı Aktarım | L2: Hukuki Sebep (KVKK → GDPR) | M2: Saklama Süresi | N2: Mevcut Doküman | O2: Kanıt Belgesi | P2: Risk / Not | Q2: Sorumlu | R2: Durum
A3: 1 | B3: Sunucu & Altyapı | C3: Şirket içi (on-premise) sunucular var mı? Lokasyonları ve üzerindeki sistemler neler? | D3: Zorunlu
A4: 2 | B4: Sunucu & Altyapı | C4: Sunucu odasına fiziksel erişim nasıl kontrol ediliyor? | D4: Zorunlu
A5: 3 | B5: Sunucu & Altyapı | C5: Veri merkezi (colocation) kullanılıyor mu? Hangi firma, hangi şehir/ülke? | D5: Zorunlu
A6: 4 | B6: Sunucu & Altyapı | C6: Sanallaştırma altyapısı nedir? (VMware, Hyper-V, Proxmox...) | D6: Opsiyonel
A7: 5 | B7: Sunucu & Altyapı | C7: Veri tabanı sistemleri neler? (MSSQL, PostgreSQL, MySQL, Oracle, MongoDB...) | D7: Zorunlu
A8: 6 | B8: Sunucu & Altyapı | C8: Hangi veri tabanlarında kişisel veri var? Envanteri çıkarılmış mı? | D8: Zorunlu
A9: 7 | B9: Sunucu & Altyapı | C9: Veri tabanlarında şifreleme (at-rest encryption) uygulanıyor mu? | D9: Zorunlu
A10: 8 | B10: Sunucu & Altyapı | C10: Dosya sunucusu/paylaşım alanları var mı? Erişim yapısı nasıl? | D10: Zorunlu
A11: 9 | B11: Sunucu & Altyapı | C11: Eski/kullanım dışı sunucularda veri kaldı mı? İmha prosedürü uygulandı mı? | D11: Zorunlu
A12: 10 | B12: Sunucu & Altyapı | C12: Sunucu bakımını kim yapıyor? Dış firma uzaktan erişiyor mu? Sözleşmesi var mı? | D12: Zorunlu
A13: 11 | B13: Sunucu & Altyapı | C13: Test/geliştirme sunucularında gerçek kişisel veri var mı? | D13: Zorunlu
A14: 12 | B14: Sunucu & Altyapı | C14: Sunucu envanteri ve ağ topolojisi dokümante edilmiş mi? | D14: Zorunlu
... A162: 160 | B162: Şifre Politikası | C162: Kritik sistem parolaları için kasa/zarf prosedürü var mı? | D162: Opsiyonel

Sheet 04-Yazılım Geliştirme
A1: 04-Yazılım Geliştirme — Veri Toplama Formu
A2: No | B2: Bölüm | C2: Soru / Süreç | D2: Zorunlu? | E2: Cevap / Açıklama | F2: İşlenen Kişisel Veri | G2: İlgili Kişi Grubu | H2: Veri Kaynağı | I2: Kullanılan Sistem | J2: Veri Alıcısı | K2: Yurtdışı Aktarım | L2: Hukuki Sebep (KVKK → GDPR) | M2: Saklama Süresi | N2: Mevcut Doküman | O2: Kanıt Belgesi | P2: Risk / Not | Q2: Sorumlu | R2: Durum
A3: 1 | B3: Repository & Kod | C3: Kaynak kod nerede barındırılıyor? (GitHub, GitLab, Bitbucket, self-hosted) | D3: Zorunlu
A4: 2 | B4: Repository & Kod | C4: Kod tabanında sabit yazılmış (hardcoded) kişisel veri var mı? | D4: Zorunlu
A5: 3 | B5: Repository & Kod | C5: Kod yorumlarında/dokümantasyonda gerçek müşteri verisi geçiyor mu? | D5: Zorunlu
A6: 4 | B6: Repository & Kod | C6: Konfigürasyon dosyalarında bağlantı bilgileri açık mı, vault'ta mı? | D6: Zorunlu
A7: 5 | B7: Repository & Kod | C7: Repo erişim seviyeleri (read/write/admin) tanımlı mı? | D7: Zorunlu
A8: 6 | B8: Repository & Kod | C8: Fork/clone kısıtlamaları var mı? Kod dışarı çıkabilir mi? | D8: Opsiyonel
A9: 7 | B9: Repository & Kod | C9: Açık kaynak katkılarında şirket kodu/verisi sızma riski değerlendirildi mi? | D9: Opsiyonel
A10: 8 | B10: Repository & Kod | C10: Git geçmişinde daha önce sızmış sır/veri temizliği yapıldı mı? | D10: Opsiyonel
A11: 9 | B11: Repository & Kod | C11: Kod sahipliği (CODEOWNERS) ve dal koruma kuralları tanımlı mı? | D11: Opsiyonel
A12: 10 | B12: Repository & Kod | C12: Müşteriye özel geliştirmelerde müşteri verisi repoya giriyor mu? | D12: Zorunlu
A13: 11 | B13: Test Verisi | C13: Test ortamlarında gerçek (production) verisi kullanılıyor mu? | D13: Zorunlu
A14: 12 | B14: Test Verisi | C14: Test verisi anonimleştirme/maskeleme aracı veya prosedürü var mı? | D14: Zorunlu
... A75: 73 | B75: Versiyon & Süreç | C75: Saklama sürelerinin otomatik uygulanması (TTL, arşivleme) kodlanmış mı? | D75: Zorunlu

Sheet 05-Satış
A1: 05-Satış — Veri Toplama Formu
A2: No | B2: Bölüm | C2: Soru / Süreç | D2: Zorunlu? | E2: Cevap / Açıklama | F2: İşlenen Kişisel Veri | G2: İlgili Kişi Grubu | H2: Veri Kaynağı | I2: Kullanılan Sistem | J2: Veri Alıcısı | K2: Yurtdışı Aktarım | L2: Hukuki Sebep (KVKK → GDPR) | M2: Saklama Süresi | N2: Mevcut Doküman | O2: Kanıt Belgesi | P2: Risk / Not | Q2: Sorumlu | R2: Durum
A3: 1 | B3: CRM | C3: Hangi CRM kullanılıyor? Sunucusu/verisi nerede barındırılıyor? | D3: Zorunlu
A4: 2 | B4: CRM | C4: CRM'de hangi kişisel veri alanları var? (ad, telefon, e-posta, notlar...) | D4: Zorunlu
A5: 3 | B5: CRM | C5: CRM'e serbest metin not girişi yapılıyor mu? İçerik kuralı var mı? | D5: Zorunlu
A6: 4 | B6: CRM | C6: CRM erişim yetkileri rol bazlı mı? Tüm satışçılar tüm müşterileri görüyor mu? | D6: Zorunlu
A7: 5 | B7: CRM | C7: CRM'den toplu veri dışa aktarma (export) kimler yapabiliyor? | D7: Zorunlu
A8: 6 | B8: CRM | C8: Kaybedilen müşteri/fırsat kayıtları ne kadar saklanıyor? | D8: Zorunlu
A9: 7 | B9: CRM | C9: CRM mobil uygulaması kullanılıyor mu? Kişisel cihazlarda mı? | D9: Opsiyonel
A10: 8 | B10: CRM | C10: CRM ile e-posta/takvim senkronizasyonu var mı? Hangi veriler akıyor? | D10: Zorunlu
A11: 9 | B11: CRM | C11: CRM sağlayıcısıyla DPA imzalanmış mı? | D11: Zorunlu
A12: 10 | B12: CRM | C12: CRM'de görev/aktivite kayıtlarında üçüncü kişi verisi tutuluyor mu? | D12: Opsiyonel
A13: 11 | B13: CRM | C13: Eski/ayrılan satışçının müşteri kayıtları nasıl devrediliyor? | D13: Opsiyonel
A14: 12 | B14: CRM | C14: CRM'deki veriler başka sistemlere (ERP, e-posta aracı) otomatik akıyor mu? | D14: Zorunlu
... A57: 55 | B57: Web Formu & Telefon | C57: Chatbot kullanılıyor mu? Toplanan veriler ve aydınlatması? | D57: Opsiyonel

Sheet 06-Pazarlama
A1: 06-Pazarlama — Veri Toplama Formu
A2: No | B2: Bölüm | C2: Soru / Süreç | D2: Zorunlu? | E2: Cevap / Açıklama | F2: İşlenen Kişisel Veri | G2: İlgili Kişi Grubu | H2: Veri Kaynağı | I2: Kullanılan Sistem | J2: Veri Alıcısı | K2: Yurtdışı Aktarım | L2: Hukuki Sebep (KVKK → GDPR) | M2: Saklama Süresi | N2: Mevcut Doküman | O2: Kanıt Belgesi | P2: Risk / Not | Q2: Sorumlu | R2: Durum
A3: 1 | B3: Web & Analitik | C3: Google Analytics kullanılıyor mu? Hangi sürüm (GA4)? IP anonimleştirme açık mı? | D3: Zorunlu
A4: 2 | B4: Web & Analitik | C4: Analytics verileri yurt dışına aktarılıyor mu? m.9 değerlendirmesi yapıldı mı? | D4: Zorunlu
A5: 3 | B5: Web & Analitik | C5: Google Tag Manager'da hangi etiketler aktif? Envanteri var mı? | D5: Zorunlu
A6: 4 | B6: Web & Analitik | C6: Site arama ve davranış verileri kişiyle eşleştiriliyor mu? (user ID takibi) | D6: Zorunlu
A7: 5 | B7: Web & Analitik | C7: Hotjar/Clarity gibi ısı haritası ve oturum kaydı araçları var mı? Maskeleme yapılıyor mu? | D7: Zorunlu
A8: 6 | B8: Web & Analitik | C8: A/B test araçları (Optimizely vb.) kullanılıyor mu? | D8: Opsiyonel
A9: 7 | B9: Web & Analitik | C9: Web sitesi hosting'i nerede? Erişim logları kim tarafından tutuluyor? | D9: Zorunlu
A10: 8 | B10: Web & Analitik | C10: Alan adı ve SSL yönetimi kimde? | D10: Opsiyonel
A11: 9 | B11: Web & Analitik | C11: Sitede üyelik/hesap sistemi var mı? Üye verileri nerede? | D11: Zorunlu
A12: 10 | B12: Web & Analitik | C12: Site içi arama sorguları loglanıyor mu? | D12: Opsiyonel
A13: 11 | B13: Web & Analitik | C13: Blog/bülten yorumlarında kişisel veri işleniyor mu? | D13: Opsiyonel
A14: 12 | B14: Web & Analitik | C14: Web sitesi birden fazla dil/ülkeye mi hizmet ediyor? (GDPR kapsam tespiti) | D14: Zorunlu
... A67: 65 | B67: Etkinlik & Webinar | C67: Etkinlik uygulamaları (mobil app, networking aracı) kişisel veri işliyor mu? | D67: Opsiyonel

Sheet 07-Sosyal Medya
A1: 07-Sosyal Medya — Veri Toplama Formu
A2: No | B2: Bölüm | C2: Soru / Süreç | D2: Zorunlu? | E2: Cevap / Açıklama | F2: İşlenen Kişisel Veri | G2: İlgili Kişi Grubu | H2: Veri Kaynağı | I2: Kullanılan Sistem | J2: Veri Alıcısı | K2: Yurtdışı Aktarım | L2: Hukuki Sebep (KVKK → GDPR) | M2: Saklama Süresi | N2: Mevcut Doküman | O2: Kanıt Belgesi | P2: Risk / Not | Q2: Sorumlu | R2: Durum
A3: 1 | B3: Hesap Yönetimi | C3: Hangi platformlarda kurumsal hesap var? (Instagram, LinkedIn, YouTube, TikTok, X...) | D3: Zorunlu
A4: 2 | B4: Hesap Yönetimi | C4: Hesapların erişim bilgileri kimde? Ortak parola mı, rol bazlı erişim mi? | D4: Zorunlu
A5: 3 | B5: Hesap Yönetimi | C5: Sosyal medya yönetim aracı (Hootsuite, Buffer...) kullanılıyor mu? | D5: Zorunlu
A6: 4 | B6: Hesap Yönetimi | C6: Ayrılan çalışanların hesap erişimleri kapatılıyor mu? | D6: Zorunlu
A7: 5 | B7: Hesap Yönetimi | C7: Hesaplarda 2FA aktif mi? | D7: Zorunlu
A8: 6 | B8: Hesap Yönetimi | C8: Platform analitiklerinde (takipçi verileri) kişisel veri işleniyor mu? | D8: Opsiyonel
A9: 7 | B9: Hesap Yönetimi | C9: Sosyal medya politikası (kurumsal + çalışan kullanımı) var mı? | D9: Zorunlu
A10: 8 | B10: Hesap Yönetimi | C10: Kriz yönetimi/itibar takibi aracı (social listening) kullanılıyor mu? | D10: Opsiyonel
A11: 9 | B11: İçerik & Görsel | C11: Paylaşılan içeriklerde çalışan/müşteri/üçüncü kişi görüntüleri var mı? | D11: Zorunlu
A12: 10 | B12: İçerik & Görsel | C12: Görsel kullanımı için izin/muvafakat formu alınıyor mu? | D12: Zorunlu
A13: 11 | B13: İçerik & Görsel | C13: Stok görsel lisansları yönetiliyor mu? | D13: Opsiyonel
A14: 12 | B14: İçerik & Görsel | C14: Müşteri logolarının/isimlerinin kullanımı sözleşmeyle izinli mi? | D14: Zorunlu
... A42: 40 | B42: DM & Mesajlaşma | C42: Şikâyet platformları (Şikâyetvar vb.) yanıtlarında kişisel veri ifşası kontrol ediliyor mu? | D42: Zorunlu

Sheet 08-Muhasebe
A1: 08-Muhasebe — Veri Toplama Formu
A2: No | B2: Bölüm | C2: Soru / Süreç | D2: Zorunlu? | E2: Cevap / Açıklama | F2: İşlenen Kişisel Veri | G2: İlgili Kişi Grubu | H2: Veri Kaynağı | I2: Kullanılan Sistem | J2: Veri Alıcısı | K2: Yurtdışı Aktarım | L2: Hukuki Sebep (KVKK → GDPR) | M2: Saklama Süresi | N2: Mevcut Doküman | O2: Kanıt Belgesi | P2: Risk / Not | Q2: Sorumlu | R2: Durum
A3: 1 | B3: Fatura & e-Belge | C3: e-Fatura/e-Arşiv entegratörü hangisi? Sözleşmesi var mı? | D3: Zorunlu
A4: 2 | B4: Fatura & e-Belge | C4: Faturalarda hangi kişisel veriler yer alıyor? (ad, T.C. no, adres) | D4: Zorunlu
A5: 3 | B5: Fatura & e-Belge | C5: Bireysel müşteri faturalarında T.C. kimlik no işleniyor mu? (VUK gereği) | D5: Zorunlu
A6: 4 | B6: Fatura & e-Belge | C6: e-İrsaliye kullanılıyor mu? Teslim alan kişi verileri işleniyor mu? | D6: Opsiyonel
A7: 5 | B7: Fatura & e-Belge | C7: Fatura verileri entegratörde ne kadar saklanıyor? | D7: Zorunlu
A8: 6 | B8: Fatura & e-Belge | C8: Kağıt fatura/fiş arşivi var mı? Nerede, nasıl korunuyor? | D8: Zorunlu
A9: 7 | B9: Fatura & e-Belge | C9: Gider pusulası/serbest meslek makbuzunda kişisel veri işleme süreçleri neler? | D9: Opsiyonel
A10: 8 | B10: Fatura & e-Belge | C10: Fatura itiraz/iade süreçlerinde ek kişisel veri toplanıyor mu? | D10: Opsiyonel
A11: 9 | B11: Fatura & e-Belge | C11: Muhasebe belgeleri VUK gereği 5 yıl / TTK gereği 10 yıl saklama kuralına bağlanmış mı? | D11: Zorunlu
A12: 10 | B12: Fatura & e-Belge | C12: e-Defter beratları ve saklama hizmeti kimden alınıyor? | D12: Opsiyonel
A13: 11 | B13: Banka & Ödeme | C13: Hangi bankalarla çalışılıyor? İnternet bankacılığı yetkilileri kimler? | D13: Zorunlu
A14: 12 | B14: Banka & Ödeme | C14: Maaş ödeme listeleri bankaya nasıl iletiliyor? (dosya formatı, kanal) | D14: Zorunlu
... A50: 48 | B50: Muhasebe Yazılımı | C50: ERP yedekleri BT yedekleme politikasına dahil mi? | D50: Zorunlu

Sheet 09-Satın Alma
A1: 09-Satın Alma — Veri Toplama Formu
A2: No | B2: Bölüm | C2: Soru / Süreç | D2: Zorunlu? | E2: Cevap / Açıklama | F2: İşlenen Kişisel Veri | G2: İlgili Kişi Grubu | H2: Veri Kaynağı | I2: Kullanılan Sistem | J2: Veri Alıcısı | K2: Yurtdışı Aktarım | L2: Hukuki Sebep (KVKK → GDPR) | M2: Saklama Süresi | N2: Mevcut Doküman | O2: Kanıt Belgesi | P2: Risk / Not | Q2: Sorumlu | R2: Durum
A3: 1 | B3: Tedarikçi Yönetimi | C3: Tedarikçi listesi nerede tutuluyor? Kaç aktif tedarikçi var? | D3: Zorunlu
A4: 2 | B4: Tedarikçi Yönetimi | C4: Tedarikçi kayıt/onboarding sürecinde hangi veriler toplanıyor? | D4: Zorunlu
A5: 3 | B5: Tedarikçi Yönetimi | C5: Tedarikçi değerlendirmesinde kişisel veri (yetkili kişi performansı) işleniyor mu? | D5: Opsiyonel
A6: 4 | B6: Tedarikçi Yönetimi | C6: Kişisel veri işleyen tedarikçiler (veri işleyenler) ayrıca işaretleniyor mu? | D6: Zorunlu
A7: 5 | B7: Tedarikçi Yönetimi | C7: Tedarikçi seçiminde veri güvenliği kriterleri soruluyor mu? (anket, denetim) | D7: Zorunlu
A8: 6 | B8: Tedarikçi Yönetimi | C8: Alt yüklenici kullanımı sözleşmelerde düzenleniyor mu? | D8: Zorunlu
A9: 7 | B9: Tedarikçi Yönetimi | C9: Tedarikçi çalışanlarının verileri (saha personeli kimlikleri) işleniyor mu? | D9: Zorunlu
A10: 8 | B10: Tedarikçi Yönetimi | C10: Tek seferlik/küçük tedarikçilerde de sözleşme süreci işletiliyor mu? | D10: Opsiyonel
A11: 9 | B11: Sözleşme & NDA/DPA | C11: Standart tedarikçi sözleşmesinde KVKK maddesi var mı? | D11: Zorunlu
A12: 10 | B12: Sözleşme & NDA/DPA | C12: Veri işleyen tedarikçilerle ayrı DPA/veri işleme protokolü imzalanıyor mu? | D12: Zorunlu
A13: 11 | B13: Sözleşme & NDA/DPA | C13: NDA'lar tek taraflı mı karşılıklı mı? Standart şablon var mı? | D13: Zorunlu
A14: 12 | B14: Sözleşme & NDA/DPA | C14: Mevcut tedarikçilerden kaçıyla DPA imzalı? Eksik listesi var mı? | D14: Zorunlu
... A42: 40 | B42: Lisans & Bulut Alımı | C42: Donanım alımlarında (ikinci el dahil) veri güvenliği kontrolü var mı? | D42: Opsiyonel

Sheet 10-Hukuk
A1: 10-Hukuk — Veri Toplama Formu
A2: No | B2: Bölüm | C2: Soru / Süreç | D2: Zorunlu? | E2: Cevap / Açıklama | F2: İşlenen Kişisel Veri | G2: İlgili Kişi Grubu | H2: Veri Kaynağı | I2: Kullanılan Sistem | J2: Veri Alıcısı | K2: Yurtdışı Aktarım | L2: Hukuki Sebep (KVKK → GDPR) | M2: Saklama Süresi | N2: Mevcut Doküman | O2: Kanıt Belgesi | P2: Risk / Not | Q2: Sorumlu | R2: Durum
A3: 1 | B3: Sözleşme Yönetimi | C3: Sözleşmeler nerede saklanıyor? (CLM yazılımı, klasör, fiziki) | D3: Zorunlu
A4: 2 | B4: Sözleşme Yönetimi | C4: Sözleşme takip listesi/veri tabanı var mı? Hangi bilgiler tutuluyor? | D4: Zorunlu
A5: 3 | B5: Sözleşme Yönetimi | C5: Sözleşmelerdeki gerçek kişi verileri (imza yetkilileri, kefiller) envanterde mi? | D5: Zorunlu
A6: 4 | B6: Sözleşme Yönetimi | C6: Sözleşme şablonlarında KVKK/veri koruma maddeleri standart mı? Kim güncelliyor? | D6: Zorunlu
A7: 5 | B7: Sözleşme Yönetimi | C7: İmza süreçleri ıslak mı, e-imza mı, DocuSign benzeri mi? | D7: Zorunlu
A8: 6 | B8: Sözleşme Yönetimi | C8: Vekâletnameler ve imza sirküleri nasıl arşivleniyor? | D8: Zorunlu
A9: 7 | B9: Sözleşme Yönetimi | C9: Sona eren sözleşmeler ve ekleri ne kadar saklanıyor? | D9: Zorunlu
A10: 8 | B10: Sözleşme Yönetimi | C10: Sözleşmelere erişim yetkisi kimlerde? | D10: Zorunlu
A11: 9 | B11: Sözleşme Yönetimi | C11: Dış hukuk bürolarıyla dosya paylaşımı nasıl yapılıyor? (e-posta, portal) | D11: Zorunlu
A12: 10 | B12: Sözleşme Yönetimi | C12: Hukuk departmanı yazışmaları için ayrı gizlilik seviyesi tanımlı mı? | D12: Opsiyonel
A13: 11 | B13: NDA & DPA | C13: Şirketin standart NDA şablonu var mı? Karşı taraf NDA'ları kim inceliyor? | D13: Zorunlu
A14: 12 | B14: NDA & DPA | C14: İmzalı NDA'ların kaydı ve süre takibi yapılıyor mu? | D14: Zorunlu
... A42: 40 | B42: KVKK Süreçleri | C42: Grup şirketleri için ayrı VERBİS kayıtları gerekli mi? Değerlendirildi mi? | D42: Opsiyonel

Sheet 11-Yönetim
A1: 11-Yönetim — Veri Toplama Formu
A2: No | B2: Bölüm | C2: Soru / Süreç | D2: Zorunlu? | E2: Cevap / Açıklama | F2: İşlenen Kişisel Veri | G2: İlgili Kişi Grubu | H2: Veri Kaynağı | I2: Kullanılan Sistem | J2: Veri Alıcısı | K2: Yurtdışı Aktarım | L2: Hukuki Sebep (KVKK → GDPR) | M2: Saklama Süresi | N2: Mevcut Doküman | O2: Kanıt Belgesi | P2: Risk / Not | Q2: Sorumlu | R2: Durum
A3: 1 | B3: YK & Kararlar | C3: Yönetim kurulu üyelerinin hangi kişisel verileri işleniyor? (kimlik, adres, imza) | D3: Zorunlu
A4: 2 | B4: YK & Kararlar | C4: YK karar defterleri ve toplantı tutanakları nerede saklanıyor? | D4: Zorunlu
A5: 3 | B5: YK & Kararlar | C5: YK üyelerine ait veriler ticaret sicili dışında kimlerle paylaşılıyor? | D5: Zorunlu
A6: 4 | B6: YK & Kararlar | C6: YK iletişimi hangi kanaldan yapılıyor? (kişisel e-posta riski) | D6: Zorunlu
A7: 5 | B7: YK & Kararlar | C7: Board portal/karar yönetim yazılımı kullanılıyor mu? | D7: Opsiyonel
A8: 6 | B8: YK & Kararlar | C8: Yönetici sorumluluk sigortası (D&O) kapsamında sigortacıya veri gidiyor mu? | D8: Opsiyonel
A9: 7 | B9: YK & Kararlar | C9: Bağımsız YK üyelerinin verileri nasıl yönetiliyor? | D9: Opsiyonel
A10: 8 | B10: YK & Kararlar | C10: Genel kurul hazirun cetvellerindeki pay sahibi verileri nasıl saklanıyor? | D10: Zorunlu
A11: 9 | B11: Ortaklar & Hisse | C11: Pay defterindeki ortak bilgileri kimler tarafından görülebiliyor? | D11: Zorunlu
A12: 10 | B12: Ortaklar & Hisse | C12: Hissedar sözleşmelerindeki kişisel veriler nasıl korunuyor? | D12: Zorunlu
A13: 11 | B13: Ortaklar & Hisse | C13: Kâr payı ödemelerinde ortak banka bilgileri nasıl işleniyor? | D13: Zorunlu
A14: 12 | B14: Ortaklar & Hisse | C14: Hisse devirlerinde alıcı/satıcı verileri hangi taraflara gidiyor? | D14: Opsiyonel
... A37: 35 | B37: Kurumsal Belgeler | C37: Şirket değerleme raporlarında kişisel veri kullanılıyor mu? | D37: Opsiyonel

Sheet 12-Güvenlik
A1: 12-Güvenlik — Veri Toplama Formu
A2: No | B2: Bölüm | C2: Soru / Süreç | D2: Zorunlu? | E2: Cevap / Açıklama | F2: İşlenen Kişisel Veri | G2: İlgili Kişi Grubu | H2: Veri Kaynağı | I2: Kullanılan Sistem | J2: Veri Alıcısı | K2: Yurtdışı Aktarım | L2: Hukuki Sebep (KVKK → GDPR) | M2: Saklama Süresi | N2: Mevcut Doküman | O2: Kanıt Belgesi | P2: Risk / Not | Q2: Sorumlu | R2: Durum
A3: 1 | B3: Kamera/CCTV | C3: Kaç kamera var? Yerleşim planı (kapsama alanları) mevcut mu? | D3: Zorunlu
A4: 2 | B4: Kamera/CCTV | C4: Kameralar hangi alanları görüyor? (ortak alan, çalışma alanı, dinlenme - yasak alan kontrolü) | D4: Zorunlu
A5: 3 | B5: Kamera/CCTV | C5: Kamera kayıtları ne kadar süre saklanıyor? Otomatik siliniyor mu? | D5: Zorunlu
A6: 4 | B6: Kamera/CCTV | C6: Kayıtlara kimler erişebiliyor? Erişim loglanıyor mu? | D6: Zorunlu
A7: 5 | B7: Kamera/CCTV | C7: Kamera aydınlatma metni ve uyarı levhaları asılı mı? (katmanlı aydınlatma) | D7: Zorunlu
A8: 6 | B8: Kamera/CCTV | C8: Kayıt sistemi (NVR/DVR) nerede? İnternete açık mı? Parolası değiştirilmiş mi? | D8: Zorunlu
A9: 7 | B9: Kamera/CCTV | C9: Bulut tabanlı kamera sistemi mi? Görüntüler yurt dışına gidiyor mu? | D9: Zorunlu
A10: 8 | B10: Kamera/CCTV | C10: Ses kaydı alınıyor mu? (orantılılık sorunu - kural olarak alınmamalı) | D10: Zorunlu
A11: 9 | B11: Kamera/CCTV | C11: Kayıt paylaşımı taleplerinde (kolluk, mahkeme, çalışan) prosedür var mı? | D11: Zorunlu
A12: 10 | B12: Kamera/CCTV | C12: Kameraların bakımını yapan firma kayıtlara erişebiliyor mu? Sözleşmesi var mı? | D12: Zorunlu
A13: 11 | B13: Kamera/CCTV | C13: Yüz tanıma veya plaka tanıma (ANPR) özelliği kullanılıyor mu? (m.6 riski) | D13: Zorunlu
A14: 12 | B14: Kamera/CCTV | C14: Kamera görüntüleri VERBİS'te 'fiziksel mekân güvenliği' kategorisinde beyan edilmiş mi? | D14: Opsiyonel
... A42: 40 | B42: Kimlik Kontrol | C42: Kargo/posta kabul kayıtlarında gönderici-alıcı verileri tutuluyor mu? | D42: Opsiyonel

Sheet 13-Temizlik
A1: 13-Temizlik — Veri Toplama Formu
A2: No | B2: Bölüm | C2: Soru / Süreç | D2: Zorunlu? | E2: Cevap / Açıklama | F2: İşlenen Kişisel Veri | G2: İlgili Kişi Grubu | H2: Veri Kaynağı | I2: Kullanılan Sistem | J2: Veri Alıcısı | K2: Yurtdışı Aktarım | L2: Hukuki Sebep (KVKK → GDPR) | M2: Saklama Süresi | N2: Mevcut Doküman | O2: Kanıt Belgesi | P2: Risk / Not | Q2: Sorumlu | R2: Durum
A3: 1 | B3: Firma & Sözleşme | C3: Temizlik hizmeti dış firmadan mı, bordrolu mu? | D3: Zorunlu
A4: 2 | B4: Firma & Sözleşme | C4: Temizlik firmasıyla sözleşmede gizlilik/KVKK hükümleri var mı? | D4: Zorunlu
A5: 3 | B5: Firma & Sözleşme | C5: Temizlik personeli listesi ve SGK bilgileri şirkete iletiliyor mu? (alt işveren yükümlülükleri) | D5: Zorunlu
A6: 4 | B6: Firma & Sözleşme | C6: Personel değişimleri şirkete bildiriliyor mu? | D6: Opsiyonel
A7: 5 | B7: Firma & Sözleşme | C7: Temizlik personeline giriş kartı veriliyor mu? Geçiş kayıtları tutuluyor mu? | D7: Zorunlu
A8: 6 | B8: Firma & Sözleşme | C8: Firma değişiminde erişim/anahtar devri prosedürü var mı? | D8: Opsiyonel
A9: 7 | B9: Firma & Sözleşme | C9: Temizlik personelinin özlük verilerini kim işliyor? (asıl işveren-alt işveren ilişkisi) | D9: Opsiyonel
A10: 8 | B10: Firma & Sözleşme | C10: Mesai dışı temizlik yapılıyorsa gözetim nasıl sağlanıyor? | D10: Zorunlu
A11: 9 | B11: Erişim Alanları | C11: Temizlik personeli hangi alanlara erişebiliyor? Kısıtlı alan listesi var mı? | D11: Zorunlu
A12: 10 | B12: Erişim Alanları | C12: Masalarda/yazıcılarda kalan belgeler riski değerlendirildi mi? (temiz masa politikası) | D12: Zorunlu
A13: 11 | B13: Erişim Alanları | C13: Çöpe atılan belgeler nasıl imha ediliyor? Kağıt imha makinesi/konteyner var mı? | D13: Zorunlu
A14: 12 | B14: Erişim Alanları | C14: Kilitli dolap/oda temizliği hangi kurala tabi? | D14: Opsiyonel
... A27: 25 | B27: NDA & Eğitim | C27: Yemekhane hizmetlisi personel listelerine (alerji, diyet) erişiyor mu? | D27: Opsiyonel

Sheet 14-Entegrasyonlar
A1: 14-Entegrasyonlar — Sistem ve Servis Envanteri
A2: No | B2: Sistem / Servis | C2: Kategori | D2: Tipik Kullanım Amacı | E2: Kullanılıyor mu? | F2: Sağlayıcı / Plan / Hesap Türü | G2: Veri Lokasyonu (ülke/region) | H2: İşlenen Kişisel Veri | I2: İlgili Kişi Grubu | J2: Yurtdışı Aktarım | K2: Sözleşme / DPA | L2: Hesap Sahibi / Admin | M2: Risk / Not | N2: Durum
A3: 1 | B3: Microsoft 365 | C3: Ofis & E-posta | D3: E-posta, ofis uygulamaları, dosya paylaşımı
A4: 2 | B4: Microsoft Entra ID (Azure AD) | C4: Kimlik Yönetimi | D4: Kimlik doğrulama, SSO
A5: 3 | B5: Google Workspace | C5: Ofis & E-posta | D5: E-posta, dokümanlar, Drive
A6: 4 | B6: AWS | C6: Bulut Altyapı | D6: Sunucu, veri tabanı, depolama
A7: 5 | B7: Microsoft Azure | C7: Bulut Altyapı | D7: Sunucu, veri tabanı, depolama
A8: 6 | B8: Google Cloud (GCP) | C8: Bulut Altyapı | D8: Sunucu, veri tabanı, depolama
A9: 7 | B9: Slack | C9: İletişim | D9: Kurum içi mesajlaşma
A10: 8 | B10: Microsoft Teams | C10: İletişim | D10: Mesajlaşma, toplantı, telefon
A11: 9 | B11: Zoom | C11: İletişim | D11: Video konferans, webinar
A12: 10 | B12: WhatsApp / WhatsApp Business | C12: İletişim | D12: Müşteri iletişimi, iç iletişim
A13: 11 | B13: OpenAI / ChatGPT | C13: Yapay Zekâ | D13: İçerik üretimi, analiz, API
A14: 12 | B14: Anthropic Claude | C14: Yapay Zekâ | D14: İçerik üretimi, analiz, API
... A47: 45 | B47: Sanal POS (iyzico, PayTR, Stripe...) | C47: Ödeme | D47: Online tahsilat
A48: 46 | B48: [Listede olmayan sistem — elle ekleyin]
A49: 47 | B49: [Listede olmayan sistem — elle ekleyin]
A50: 48 | B50: [Listede olmayan sistem — elle ekleyin]
A51: 49 | B51: [Listede olmayan sistem — elle ekleyin]
A52: 50 | B52: [Listede olmayan sistem — elle ekleyin]
A53: 51 | B53: [Listede olmayan sistem — elle ekleyin]
A54: 52 | B54: [Listede olmayan sistem — elle ekleyin]
A55: 53 | B55: [Listede olmayan sistem — elle ekleyin]
A56: 54 | B56: [Listede olmayan sistem — elle ekleyin]
A57: 55 | B57: [Listede olmayan sistem — elle ekleyin]
A58: 56 | B58: [Listede olmayan sistem — elle ekleyin]
A59: 57 | B59: [Listede olmayan sistem — elle ekleyin]

Sheet 15-Kanıt Belgeleri
A1: 15-Kanıt Belgeleri — Yüklenecek Belge Kontrol Listesi
A2: No | B2: Kategori | C2: Belge Adı | D2: İlgili Sekme | E2: Zorunlu? | F2: Durum | G2: Dosya Adı / Konum | H2: Sorumlu | I2: Not
A3: 1 | B3: Politika & Prosedür | C3: Kişisel veri saklama ve imha politikası | D3: 10-Hukuk | E3: Zorunlu
A4: 2 | B4: Politika & Prosedür | C4: Kişisel veri işleme (genel KVKK) politikası | D4: 10-Hukuk | E4: Zorunlu
A5: 3 | B5: Politika & Prosedür | C5: Bilgi güvenliği politikası | D5: 03-Bilgi Teknolojileri | E5: Zorunlu
A6: 4 | B6: Politika & Prosedür | C6: Özel nitelikli veri işleme politikası | D6: 10-Hukuk | E6: Zorunlu
A7: 5 | B7: Politika & Prosedür | C7: Erişim yetkilendirme prosedürü | D7: 03-Bilgi Teknolojileri | E7: Zorunlu
A8: 6 | B8: Politika & Prosedür | C8: Parola politikası | D8: 03-Bilgi Teknolojileri | E8: Zorunlu
A9: 7 | B9: Politika & Prosedür | C9: Uzaktan çalışma politikası | D9: 02-İnsan Kaynakları | E9: Opsiyonel
A10: 8 | B10: Politika & Prosedür | C10: BYOD / mobil cihaz politikası | D10: 03-Bilgi Teknolojileri | E10: Opsiyonel
A11: 9 | B11: Politika & Prosedür | C11: Yapay zekâ kullanım politikası | D11: 03-Bilgi Teknolojileri | E11: Zorunlu
A12: 10 | B12: Politika & Prosedür | C12: Sosyal medya politikası | D12: 07-Sosyal Medya | E12: Opsiyonel
A13: 11 | B13: Politika & Prosedür | C13: Temiz masa / temiz ekran politikası | D13: 12-Güvenlik | E13: Opsiyonel
A14: 12 | B14: Politika & Prosedür | C14: Veri ihlali müdahale planı | D14: 03-Bilgi Teknolojileri | E14: Zorunlu
... A77: 75 | B77: Kayıt & Envanter | C77: Ticaret sicil gazetesi / imza sirküleri | D77: 11-Yönetim | E77: Opsiyonel

Sheet Sayfa1
A1: İLGİLİ KİŞİ | B1: KİŞİSEL VERİ KATEGORİSİ (ÜST)
A2: Çalışan | B2: Biyometrik Veri
A3: Çalışan Adayı | B3: Ceza Mahkumiyeti ve Güvenlik Tedbirleri
A4: Denek | B4: Cinsel Hayat
A5: Diğer | B5: Dernek Üyeliği
A6: Habere konu kişi | B6: Diğer Bilgiler
A7: Hissedar/Ortak | B7: Felsefi İnanç, Din, Mezhep ve Diğer İnançlar
A8: Potansiyel Ürün veya Hizmet Alıcısı | B8: Finans
A9: Sınav adayı | B9: Fiziksel Mekân Güvenliği
A10: Stajyer | B10: Genetik Veri
A11: Tedarikçi Çalışanı | B11: Görsel ve İşitsel Kayıtlar
A12: Tedarikçi Yetkilisi | B12: Hukuki İşlem
... A16: Ziyaretçi | B16: Kılık ve Kıyafet
B17: Kimlik
B18: Lokasyon
B19: Mesleki Deneyim
B20: Müşteri İşlem
B21: Özlük
B22: Pazarlama
B23: Risk Yönetimi
B24: Sağlık Bilgileri
B25: Sendika Üyeliği
B26: Siyasi Düşünce Bilgileri
B27: Vakıf Üyeliği

Sheet Listeler
A1: KISI | B1: KAYNAK | C1: YURTDISI | D1: HUKUKI | E1: DURUM | F1: DOKUMAN | G1: KANIT | H1: KULLANIM | I1: SOZLESME
A2: Çalışan | B2: İlgili kişinin kendisi | C2: Evet | D2: 5/1 Açık Rıza (GDPR 6/1-a) | E2: Dolduruldu | F2: Var | G2: Eklendi | H2: Evet | I2: Var
A3: Çalışan Adayı | B3: Başka veri sorumlusu | C3: Hayır | D3: 5/2-a Kanunlarda Öngörülme (GDPR 6/1-c) | E3: Kısmen Dolduruldu | F3: Kısmen | G3: Eklenecek | H3: Hayır | I3: Yok
A4: Stajyer | B4: Kamu kurumu | C4: Muhtemel (bulut) | D4: 5/2-b Fiili İmkânsızlık (GDPR 6/1-d) | E4: Bilinmiyor | F4: Yok | G4: Yok | H4: Kısmen | I4: Kısmen (NDA var, DPA yok)
A5: Eski Çalışan | B5: Otomatik sistem / log | C5: Bilinmiyor | D5: 5/2-c Sözleşmenin Kurulması/İfası (GDPR 6/1-b) | E5: Uygulanamaz | F5: Bilinmiyor | G5: Uygulanamaz | H5: Değerlendiriliyor | I5: Bilinmiyor
A6: Çalışan Yakını | B6: Çerez / izleme teknolojisi | D6: 5/2-ç Hukuki Yükümlülük (GDPR 6/1-c) | H6: Bilinmiyor
A7: Müşteri (Ürün/Hizmet Alan) | B7: Üçüncü taraf platform | D7: 5/2-d İlgili Kişinin Alenileştirmesi
A8: Potansiyel Müşteri | B8: Karma / Birden Fazla | D8: 5/2-e Hakkın Tesisi/Kullanılması/Korunması (GDPR 6/1-f)
A9: Müşteri Yetkilisi/Çalışanı | B9: Bilinmiyor | D9: 5/2-f Meşru Menfaat (GDPR 6/1-f)
A10: Tedarikçi Yetkilisi/Çalışanı | D10: m.6 Özel Nitelikli Veri Şartı (GDPR art.9)
A11: Ziyaretçi | D11: Birden Fazla Sebep (nota yazın)
A12: Web Sitesi Ziyaretçisi | D12: Belirlenmedi / Bilinmiyor
A13: Kullanıcı (Ürün/Uygulama)
A14: Hissedar/Ortak
A15: Yönetim Kurulu Üyesi
A16: Karma / Birden Fazla Grup
A17: Diğer
A18: Bilinmiyor
